remote_host-0.2.0.dist-info/METADATA
remote_host-0.2.0.dist-info/WHEEL
remote_host/__init__.py
remote_host/base_remote_host.py
remote_host/examples/__init__.py
remote_host/examples/example.py
remote_host/linux_remote_host.py
remote_host/objects.py
remote_host/windows_remote_host.py
remote_host-0.2.0.dist-info/RECORD
